easyttuimenus/__init__.py
easyttuimenus/__init__.pyi
easyttuimenus/main.py
easyttuimenus/main.pyi
easyttuimenus-1.0.3.dist-info/licenses/LICENSE
easyttuimenus-1.0.3.dist-info/METADATA
easyttuimenus-1.0.3.dist-info/WHEEL
easyttuimenus-1.0.3.dist-info/top_level.txt
easyttuimenus-1.0.3.dist-info/RECORD
