Metadata-Version: 2.4
Name: easyttuimenus
Version: 1.0.3
Summary: Write simple UI for your code in seconds in a unified way using Easy TTUI Menus
Author: sarcasticDweller
Requires-Python: >=3.6
License-File: LICENSE
Dynamic: author
Dynamic: description
Dynamic: description-content-type
Dynamic: license-file
Dynamic: requires-python
Dynamic: summary
